{
    "CFG": {
        "BRANCH": "WRLINUX_10_17_BASE",
        "CACHE": "config/index-cache/layers_wrs_com",
        "DESCRIPTION": "Wind River Developer Layer Index",
        "TYPE": "restapi-web",
        "URL": "http://layers.wrs.com/layerindex/api/"
    },
    "branches": [
        {
            "bitbake_branch": "wr-10.17-20180418",
            "id": 48,
            "name": "WRLINUX_10_17_BASE",
            "short_description": "Wind River Linux 10_17 Baseline",
            "sort_priority": 9,
            "update_environment": null,
            "updated": "2018-04-25T08:04:56+0000",
            "updates_enabled": true
        }
    ],
    "distros": [
        {
            "description": "Wind River Linux CGL",
            "id": 3110,
            "layerbranch": 166277,
            "name": "wrlinux-cgl",
            "updated": "2018-04-28T03:04:31+0000"
        }
    ],
    "layerBranches": [
        {
            "actual_branch": "wr-10.17-20180418",
            "branch": 48,
            "collection": "core",
            "id": 165030,
            "layer": 1,
            "updated": "2018-05-07T11:05:59+0000",
            "vcs_last_commit": "2018-05-07T05:05:11+0000",
            "vcs_last_fetch": "2018-05-07T11:05:59+0000",
            "vcs_last_rev": "1ccdeb69a75a9b4cb9d4655be02abe2503381de5",
            "vcs_subdir": "meta",
            "version": "11",
            "yp_compatible_version": null
        },
        {
            "actual_branch": "",
            "branch": 48,
            "collection": "wr-template",
            "id": 165069,
            "layer": 55,
            "updated": "2018-05-07T11:05:08+0000",
            "vcs_last_commit": "2017-12-13T05:12:44+0000",
            "vcs_last_fetch": "2018-05-07T11:05:08+0000",
            "vcs_last_rev": "0a6c6f593d8c13216b897c1731b289c15f571393",
            "vcs_subdir": "",
            "version": "1",
            "yp_compatible_version": null
        },
        {
            "actual_branch": "wr-10.17-20171018",
            "branch": 48,
            "collection": "meta-initramfs",
            "id": 165074,
            "layer": 4,
            "updated": "2018-05-07T11:05:59+0000",
            "vcs_last_commit": "2017-10-18T06:10:28+0000",
            "vcs_last_fetch": "2018-05-07T11:05:59+0000",
            "vcs_last_rev": "94e9e03da4d5539963d6f536f03c5d3cb0e1d4f1",
            "vcs_subdir": "meta-initramfs",
            "version": null,
            "yp_compatible_version": null
        },
        {
            "actual_branch": "wr-10.17-20171018",
            "branch": 48,
            "collection": "xfce-layer",
            "id": 165075,
            "layer": 5,
            "updated": "2018-05-07T11:05:17+0000",
            "vcs_last_commit": "2017-11-09T03:11:50+0000",
            "vcs_last_fetch": "2018-05-07T11:05:17+0000",
            "vcs_last_rev": "34a5c32045afae17875904d49b7cbf6490872365",
            "vcs_subdir": "meta-xfce",
            "version": "1",
            "yp_compatible_version": null
        },
        {
            "actual_branch": "wr-10.17-20171018",
            "branch": 48,
            "collection": "openembedded-layer",
            "id": 165076,
            "layer": 7,
            "updated": "2018-05-07T11:05:00+0000",
            "vcs_last_commit": "2018-02-12T01:02:22+0000",
            "vcs_last_fetch": "2018-05-07T11:05:00+0000",
            "vcs_last_rev": "274ce9bf5d71a6a02d0bb09832423d7dff1ed548",
            "vcs_subdir": "meta-oe",
            "version": "1",
            "yp_compatible_version": null
        },
        {
            "actual_branch": "wr-10.17-20171018",
            "branch": 48,
            "collection": "filesystems-layer",
            "id": 165077,
            "layer": 8,
            "updated": "2018-05-07T11:05:00+0000",
            "vcs_last_commit": "2017-10-18T06:10:28+0000",
            "vcs_last_fetch": "2018-05-07T11:05:00+0000",
            "vcs_last_rev": "94e9e03da4d5539963d6f536f03c5d3cb0e1d4f1",
            "vcs_subdir": "meta-filesystems",
            "version": "1",
            "yp_compatible_version": null
        },
        {
            "actual_branch": "wr-10.17-20171018",
            "branch": 48,
            "collection": "webserver",
            "id": 165078,
            "layer": 10,
            "updated": "2018-05-07T11:05:01+0000",
            "vcs_last_commit": "2017-10-18T06:10:28+0000",
            "vcs_last_fetch": "2018-05-07T11:05:01+0000",
            "vcs_last_rev": "94e9e03da4d5539963d6f536f03c5d3cb0e1d4f1",
            "vcs_subdir": "meta-webserver",
            "version": "1",
            "yp_compatible_version": null
        },
        {
            "actual_branch": "wr-10.17-20171018",
            "branch": 48,
            "collection": "networking-layer",
            "id": 165079,
            "layer": 11,
            "updated": "2018-05-07T11:05:13+0000",
            "vcs_last_commit": "2018-05-07T06:05:45+0000",
            "vcs_last_fetch": "2018-05-07T11:05:13+0000",
            "vcs_last_rev": "576d9f86026845a702c27a225030f8315c7709bb",
            "vcs_subdir": "meta-networking",
            "version": "1",
            "yp_compatible_version": null
        },
        {
            "actual_branch": "wr-10.17-20171018",
            "branch": 48,
            "collection": "meta-python",
            "id": 165080,
            "layer": 12,
            "updated": "2018-05-07T11:05:01+0000",
            "vcs_last_commit": "2017-12-25T05:12:48+0000",
            "vcs_last_fetch": "2018-05-07T11:05:01+0000",
            "vcs_last_rev": "4b81f9b6ab2d867eb01ca1ab2c86bd4ecadec80b",
            "vcs_subdir": "meta-python",
            "version": "1",
            "yp_compatible_version": null
        },
        {
            "actual_branch": "wr-10.17-20171018",
            "branch": 48,
            "collection": "perl-layer",
            "id": 165081,
            "layer": 13,
            "updated": "2018-05-07T11:05:02+0000",
            "vcs_last_commit": "2017-10-18T06:10:28+0000",
            "vcs_last_fetch": "2018-05-07T11:05:02+0000",
            "vcs_last_rev": "f09a3b9f43c51f7055afee9126a770f44d4b5cb3",
            "vcs_subdir": "meta-perl",
            "version": "1",
            "yp_compatible_version": null
        },
        {
            "actual_branch": "wr-10.17-20171018",
            "branch": 48,
            "collection": "gnome-layer",
            "id": 165086,
            "layer": 15,
            "updated": "2018-05-07T11:05:13+0000",
            "vcs_last_commit": "2018-02-12T01:02:22+0000",
            "vcs_last_fetch": "2018-05-07T11:05:13+0000",
            "vcs_last_rev": "274ce9bf5d71a6a02d0bb09832423d7dff1ed548",
            "vcs_subdir": "meta-gnome",
            "version": "1",
            "yp_compatible_version": null
        },
        {
            "actual_branch": "wr-10.17-20171018",
            "branch": 48,
            "collection": "multimedia-layer",
            "id": 165104,
            "layer": 16,
            "updated": "2018-05-07T11:05:02+0000",
            "vcs_last_commit": "2017-10-18T06:10:28+0000",
            "vcs_last_fetch": "2018-05-07T11:05:02+0000",
            "vcs_last_rev": "94e9e03da4d5539963d6f536f03c5d3cb0e1d4f1",
            "vcs_subdir": "meta-multimedia",
            "version": "1",
            "yp_compatible_version": null
        },
        {
            "actual_branch": "wr-10.17-20171018",
            "branch": 48,
            "collection": "security",
            "id": 165120,
            "layer": 18,
            "updated": "2018-05-07T11:05:14+0000",
            "vcs_last_commit": "2017-10-18T01:10:06+0000",
            "vcs_last_fetch": "2018-05-07T11:05:14+0000",
            "vcs_last_rev": "779bc1ec006ebef344d2bdfd00f2170a9273fee9",
            "vcs_subdir": "",
            "version": null,
            "yp_compatible_version": null
        },
        {
            "actual_branch": "wr-10.17-20170926",
            "branch": 48,
            "collection": "selinux",
            "id": 165135,
            "layer": 20,
            "updated": "2018-05-07T11:05:03+0000",
            "vcs_last_commit": "2018-02-05T06:02:19+0000",
            "vcs_last_fetch": "2018-05-07T11:05:03+0000",
            "vcs_last_rev": "a4c4067e65e4f014f16607656cc1affd3ad01988",
            "vcs_subdir": "",
            "version": "1",
            "yp_compatible_version": null
        },
        {
            "actual_branch": "wr-10.17-20171018",
            "branch": 48,
            "collection": "virtualization-layer",
            "id": 165142,
            "layer": 45,
            "updated": "2018-05-07T11:05:15+0000",
            "vcs_last_commit": "2018-03-21T10:03:23+0000",
            "vcs_last_fetch": "2018-05-07T11:05:15+0000",
            "vcs_last_rev": "f909adbe312c7357a9e25261a77de2dea03f4d95",
            "vcs_subdir": "",
            "version": "1",
            "yp_compatible_version": null
        },
        {
            "actual_branch": "wr-10.17-20171009",
            "branch": 48,
            "collection": "realtime",
            "id": 165168,
            "layer": 48,
            "updated": "2018-05-07T11:05:05+0000",
            "vcs_last_commit": "2017-11-17T02:11:37+0000",
            "vcs_last_fetch": "2018-05-07T11:05:05+0000",
            "vcs_last_rev": "bf00aeb8978806c3fec519cf18f8df6b4a55512b",
            "vcs_subdir": "",
            "version": "1",
            "yp_compatible_version": null
        },
        {
            "actual_branch": "",
            "branch": 48,
            "collection": "wrlinux",
            "id": 166260,
            "layer": 49,
            "updated": "2018-05-07T11:05:20+0000",
            "vcs_last_commit": "2018-05-07T09:05:15+0000",
            "vcs_last_fetch": "2018-05-07T11:05:20+0000",
            "vcs_last_rev": "8d13d2d032ad39d38e5d1f36a6a8248c3a6fd7ae",
            "vcs_subdir": "",
            "version": "2",
            "yp_compatible_version": null
        },
        {
            "actual_branch": "",
            "branch": 48,
            "collection": "wrlinux-distro",
            "id": 166275,
            "layer": 164,
            "updated": "2018-05-07T11:05:27+0000",
            "vcs_last_commit": "2018-05-07T02:05:10+0000",
            "vcs_last_fetch": "2018-05-07T11:05:27+0000",
            "vcs_last_rev": "f32779bcb79596e7a61bcd0b62674af9098e1008",
            "vcs_subdir": "wrlinux-distro",
            "version": "1",
            "yp_compatible_version": null
        },
        {
            "actual_branch": "wr-10.17-20171018",
            "branch": 48,
            "collection": "cgl-common",
            "id": 166276,
            "layer": 172,
            "updated": "2018-05-07T11:05:15+0000",
            "vcs_last_commit": "2018-03-15T07:03:22+0000",
            "vcs_last_fetch": "2018-05-07T11:05:15+0000",
            "vcs_last_rev": "22e606a04d7b625f97d24713f75b8236074184b1",
            "vcs_subdir": "meta-cgl-common",
            "version": null,
            "yp_compatible_version": null
        },
        {
            "actual_branch": "",
            "branch": 48,
            "collection": "wrlinux-cgl",
            "id": 166277,
            "layer": 176,
            "updated": "2018-05-07T11:05:28+0000",
            "vcs_last_commit": "2018-03-01T08:03:06+0000",
            "vcs_last_fetch": "2018-05-07T11:05:28+0000",
            "vcs_last_rev": "1901559e9da0a8d0cfecbfb618e733abba443f53",
            "vcs_subdir": "wrlinux-cgl",
            "version": "1",
            "yp_compatible_version": null
        }
    ],
    "layerDependencies": [
        {
            "dependency": 174,
            "id": 18436,
            "layerbranch": 166277,
            "required": false
        },
        {
            "dependency": 5,
            "id": 21074,
            "layerbranch": 166277,
            "required": true
        },
        {
            "dependency": 172,
            "id": 21165,
            "layerbranch": 166277,
            "required": true
        },
        {
            "dependency": 1,
            "id": 21166,
            "layerbranch": 166277,
            "required": true
        },
        {
            "dependency": 8,
            "id": 21167,
            "layerbranch": 166277,
            "required": true
        },
        {
            "dependency": 15,
            "id": 21168,
            "layerbranch": 166277,
            "required": true
        },
        {
            "dependency": 4,
            "id": 21169,
            "layerbranch": 166277,
            "required": true
        },
        {
            "dependency": 12,
            "id": 21170,
            "layerbranch": 166277,
            "required": true
        },
        {
            "dependency": 16,
            "id": 21171,
            "layerbranch": 166277,
            "required": true
        },
        {
            "dependency": 11,
            "id": 21172,
            "layerbranch": 166277,
            "required": true
        },
        {
            "dependency": 7,
            "id": 21173,
            "layerbranch": 166277,
            "required": true
        },
        {
            "dependency": 13,
            "id": 21174,
            "layerbranch": 166277,
            "required": true
        },
        {
            "dependency": 48,
            "id": 21175,
            "layerbranch": 166277,
            "required": true
        },
        {
            "dependency": 18,
            "id": 21176,
            "layerbranch": 166277,
            "required": true
        },
        {
            "dependency": 20,
            "id": 21177,
            "layerbranch": 166277,
            "required": true
        },
        {
            "dependency": 45,
            "id": 21178,
            "layerbranch": 166277,
            "required": true
        },
        {
            "dependency": 10,
            "id": 21179,
            "layerbranch": 166277,
            "required": true
        },
        {
            "dependency": 55,
            "id": 21180,
            "layerbranch": 166277,
            "required": true
        },
        {
            "dependency": 49,
            "id": 21181,
            "layerbranch": 166277,
            "required": true
        },
        {
            "dependency": 164,
            "id": 21182,
            "layerbranch": 166277,
            "required": true
        }
    ],
    "layerItems": [
        {
            "classic": false,
            "description": "OpenEmbedded-Core is a layer containing the core metadata for current versions\r\nof OpenEmbedded. It is distro-less (can build a functional image with\r\nDISTRO = \"nodistro\") and contains only emulated machine support.",
            "id": 1,
            "index_preference": 1000,
            "layer_type": "A",
            "mailing_list_url": "",
            "name": "openembedded-core",
            "status": "P",
            "summary": "Core Metadata",
            "updated": "2017-08-25T17:08:12+0000",
            "usage_url": "README",
            "vcs_url": "#BASE_URL#/oe-core",
            "vcs_web_file_base_url": "",
            "vcs_web_tree_base_url": "",
            "vcs_web_url": ""
        },
        {
            "classic": false,
            "description": "This layer contains the metadata necessary to build the klibc library and\r\nutilities (shared and static) plus other tools useful for the creation of\r\nsmall-sized initramfs.",
            "id": 4,
            "index_preference": 800,
            "layer_type": "A",
            "mailing_list_url": "",
            "name": "meta-initramfs",
            "status": "P",
            "summary": "klibc library and related utilities for building an initramfs",
            "updated": "2017-08-25T17:08:07+0000",
            "usage_url": "README",
            "vcs_url": "#BASE_URL#/meta-openembedded",
            "vcs_web_file_base_url": "",
            "vcs_web_tree_base_url": "",
            "vcs_web_url": ""
        },
        {
            "classic": false,
            "description": "The XFCE Desktop software and related components.",
            "id": 5,
            "index_preference": 800,
            "layer_type": "A",
            "mailing_list_url": "",
            "name": "meta-xfce",
            "status": "P",
            "summary": "XFCE Desktop components",
            "updated": "2017-08-25T17:08:26+0000",
            "usage_url": "README",
            "vcs_url": "#BASE_URL#/meta-openembedded",
            "vcs_web_file_base_url": "",
            "vcs_web_tree_base_url": "",
            "vcs_web_url": ""
        },
        {
            "classic": false,
            "description": "Additional shared OE metadata",
            "id": 7,
            "index_preference": 0,
            "layer_type": "A",
            "mailing_list_url": "",
            "name": "meta-oe",
            "status": "P",
            "summary": "Additional shared OE metadata",
            "updated": "2017-08-25T17:08:40+0000",
            "usage_url": "README",
            "vcs_url": "#BASE_URL#/meta-openembedded",
            "vcs_web_file_base_url": "",
            "vcs_web_tree_base_url": "",
            "vcs_web_url": ""
        },
        {
            "classic": false,
            "description": "Filesystem related libraries and programs.  Includes support for FUSE and related components.",
            "id": 8,
            "index_preference": 0,
            "layer_type": "A",
            "mailing_list_url": "",
            "name": "meta-filesystems",
            "status": "P",
            "summary": "Filesystem related libraries and programs",
            "updated": "2017-08-25T17:08:01+0000",
            "usage_url": "README",
            "vcs_url": "#BASE_URL#/meta-openembedded",
            "vcs_web_file_base_url": "",
            "vcs_web_tree_base_url": "",
            "vcs_web_url": ""
        },
        {
            "classic": false,
            "description": "This layer provides support for building web servers, web-based\r\napplications and related software.",
            "id": 10,
            "index_preference": 800,
            "layer_type": "A",
            "mailing_list_url": "",
            "name": "meta-webserver",
            "status": "P",
            "summary": "Web server software and web-based applications",
            "updated": "2017-08-25T17:08:06+0000",
            "usage_url": "README",
            "vcs_url": "#BASE_URL#/meta-openembedded",
            "vcs_web_file_base_url": "",
            "vcs_web_tree_base_url": "",
            "vcs_web_url": ""
        },
        {
            "classic": false,
            "description": "This layer is intended to be a central point for networking-related\r\npackages and configuration.  It should be useful directly on top of\r\noe-core and compliments meta-openembedded.  It should be primarily useful\r\nto the following groups:",
            "id": 11,
            "index_preference": 800,
            "layer_type": "A",
            "mailing_list_url": "",
            "name": "meta-networking",
            "status": "P",
            "summary": "Networking-related packages and configuration",
            "updated": "2017-08-25T17:08:48+0000",
            "usage_url": "README",
            "vcs_url": "#BASE_URL#/meta-openembedded",
            "vcs_web_file_base_url": "",
            "vcs_web_tree_base_url": "",
            "vcs_web_url": ""
        },
        {
            "classic": false,
            "description": "PYTHON Language related items",
            "id": 12,
            "index_preference": 800,
            "layer_type": "A",
            "mailing_list_url": "",
            "name": "meta-python",
            "status": "P",
            "summary": "PYTHON Language related items",
            "updated": "2017-08-25T17:08:36+0000",
            "usage_url": "README",
            "vcs_url": "#BASE_URL#/meta-openembedded",
            "vcs_web_file_base_url": "",
            "vcs_web_tree_base_url": "",
            "vcs_web_url": ""
        },
        {
            "classic": false,
            "description": "PERL language and related items",
            "id": 13,
            "index_preference": 800,
            "layer_type": "A",
            "mailing_list_url": "",
            "name": "meta-perl",
            "status": "P",
            "summary": "PERL language and related items",
            "updated": "2017-08-25T17:08:07+0000",
            "usage_url": "README",
            "vcs_url": "#BASE_URL#/meta-openembedded",
            "vcs_web_file_base_url": "",
            "vcs_web_tree_base_url": "",
            "vcs_web_url": ""
        },
        {
            "classic": false,
            "description": "GNOME desktop environment components",
            "id": 15,
            "index_preference": 800,
            "layer_type": "A",
            "mailing_list_url": "",
            "name": "meta-gnome",
            "status": "P",
            "summary": "GNOME desktop environment components",
            "updated": "2017-08-25T17:08:27+0000",
            "usage_url": "README",
            "vcs_url": "#BASE_URL#/meta-openembedded",
            "vcs_web_file_base_url": "",
            "vcs_web_tree_base_url": "",
            "vcs_web_url": ""
        },
        {
            "classic": false,
            "description": "Multimedia related components such as gstreamer, alsa, dvb, etc.",
            "id": 16,
            "index_preference": 800,
            "layer_type": "A",
            "mailing_list_url": "",
            "name": "meta-multimedia",
            "status": "P",
            "summary": "Multimedia related components",
            "updated": "2017-08-25T17:08:28+0000",
            "usage_url": "README",
            "vcs_url": "#BASE_URL#/meta-openembedded",
            "vcs_web_file_base_url": "",
            "vcs_web_tree_base_url": "",
            "vcs_web_url": ""
        },
        {
            "classic": false,
            "description": "This layer provides security tools, hardening tools for Linux kernels\r\nand libraries for implementing security mechanisms.",
            "id": 18,
            "index_preference": 800,
            "layer_type": "A",
            "mailing_list_url": "",
            "name": "meta-security",
            "status": "P",
            "summary": "Security tools and libraries",
            "updated": "2017-08-25T17:08:09+0000",
            "usage_url": "README",
            "vcs_url": "#BASE_URL#/meta-security",
            "vcs_web_file_base_url": "",
            "vcs_web_tree_base_url": "",
            "vcs_web_url": ""
        },
        {
            "classic": false,
            "description": "This layer's purpose is enabling SE Linux support when used with Poky.",
            "id": 20,
            "index_preference": 800,
            "layer_type": "A",
            "mailing_list_url": "",
            "name": "meta-selinux",
            "status": "P",
            "summary": "SE Linux support",
            "updated": "2017-08-25T17:08:31+0000",
            "usage_url": "README",
            "vcs_url": "#BASE_URL#/meta-selinux",
            "vcs_web_file_base_url": "",
            "vcs_web_tree_base_url": "",
            "vcs_web_url": ""
        },
        {
            "classic": false,
            "description": "This layer provides lxc package build for Wind River Linux.  It\r\nis required by most other layers that Wind River provides.",
            "id": 45,
            "index_preference": 900,
            "layer_type": "A",
            "mailing_list_url": "",
            "name": "meta-virtualization",
            "status": "P",
            "summary": "Virtualization related components",
            "updated": "2017-08-25T17:08:52+0000",
            "usage_url": "README",
            "vcs_url": "#BASE_URL#/meta-virtualization",
            "vcs_web_file_base_url": "",
            "vcs_web_tree_base_url": "",
            "vcs_web_url": ""
        },
        {
            "classic": false,
            "description": "This layer is intended to be a central point for realtime related kernel and\r\nsystem development. It also contains utilities, and configuration useful for\r\ntuning a realtime system. It should be useful directly on top of oe-core.  It\r\nshould be primarily useful to the following groups:",
            "id": 48,
            "index_preference": 900,
            "layer_type": "A",
            "mailing_list_url": "",
            "name": "meta-realtime",
            "status": "P",
            "summary": "Realtime related kernel components",
            "updated": "2017-08-25T17:08:33+0000",
            "usage_url": "README",
            "vcs_url": "#BASE_URL#/meta-realtime",
            "vcs_web_file_base_url": "",
            "vcs_web_tree_base_url": "",
            "vcs_web_url": ""
        },
        {
            "classic": false,
            "description": "This layer provides the Wind River Linux distribution definitions, \r\ndistribution-specific integration and bug fixes, and other wrlinux components.",
            "id": 49,
            "index_preference": 900,
            "layer_type": "D",
            "mailing_list_url": "",
            "name": "wrlinux",
            "status": "P",
            "summary": "Wind River Linux distribution definitions",
            "updated": "2017-03-01T21:03:25+0000",
            "usage_url": "README",
            "vcs_url": "#BASE_URL#/wrlinux",
            "vcs_web_file_base_url": "",
            "vcs_web_tree_base_url": "",
            "vcs_web_url": ""
        },
        {
            "classic": false,
            "description": "This layer provides template processing support to OpenEmbedded.  Wind River\r\ntemplates are a mechanism that permit various configurations to be enabled\r\nwith a simple setting.",
            "id": 55,
            "index_preference": 900,
            "layer_type": "A",
            "mailing_list_url": "",
            "name": "wr-template",
            "status": "P",
            "summary": "Wind River Template Support",
            "updated": "2017-01-20T16:01:26+0000",
            "usage_url": "README",
            "vcs_url": "#BASE_URL#/wr-template",
            "vcs_web_file_base_url": "",
            "vcs_web_tree_base_url": "",
            "vcs_web_url": ""
        },
        {
            "classic": false,
            "description": "The base distribution settings for wrlinux and related DISTRO items.",
            "id": 164,
            "index_preference": 0,
            "layer_type": "D",
            "mailing_list_url": "",
            "name": "wrlinux-distro",
            "status": "P",
            "summary": "Wind River Linux base distribution layer",
            "updated": "2017-09-05T12:09:34+0000",
            "usage_url": "",
            "vcs_url": "#BASE_URL#/wrlinux",
            "vcs_web_file_base_url": "",
            "vcs_web_tree_base_url": "",
            "vcs_web_url": ""
        },
        {
            "classic": false,
            "description": "Carrier Grade Linux related components",
            "id": 172,
            "index_preference": 0,
            "layer_type": "A",
            "mailing_list_url": "",
            "name": "meta-cgl-common",
            "status": "P",
            "summary": "Carrier Grade Linux related components",
            "updated": "2017-09-14T16:09:45+0000",
            "usage_url": "",
            "vcs_url": "#BASE_URL#/meta-cgl",
            "vcs_web_file_base_url": "",
            "vcs_web_tree_base_url": "",
            "vcs_web_url": ""
        },
        {
            "classic": false,
            "description": "This layer is derived from the Wind River Linux Carrier Grade Profile and contains the images and recipes required to build images related to Carrier Grade Linux.",
            "id": 176,
            "index_preference": 0,
            "layer_type": "D",
            "mailing_list_url": "",
            "name": "wrlinux-cgl",
            "status": "P",
            "summary": "Carrier Grade Linux",
            "updated": "2017-09-29T21:09:29+0000",
            "usage_url": "",
            "vcs_url": "#BASE_URL#/wrlinux",
            "vcs_web_file_base_url": "",
            "vcs_web_tree_base_url": "",
            "vcs_web_url": ""
        }
    ],
    "machines": [],
    "recipes": [
        {
            "bbclassextend": " ",
            "blacklisted": "",
            "bugtracker": "",
            "description": "freeDiameter is an open source Diameter protocol implementation. It provides an extensible platform for deploying a Diameter network for your Authentication, Authorization and Accounting needs.",
            "filename": "freediameter_1.2.1.bb",
            "filepath": "recipes-cgl/freediameter",
            "homepage": "http://www.freediameter.net",
            "id": 621725,
            "inherits": "cmake ptest systemd update-rc.d",
            "layerbranch": 166277,
            "license": "BSD",
            "pn": "freediameter",
            "provides": "freediameter ",
            "pv": "1.2.1",
            "section": "base",
            "summary": "An open source implementation of the diameter protocol",
            "updated": "2018-04-28T03:04:31+0000"
        },
        {
            "bbclassextend": " ",
            "blacklisted": "",
            "bugtracker": "",
            "description": "Based on Linux container and underlying namespace, vrf package provides a framework to make easier to establish virtual router/switch with WRLinux",
            "filename": "vrf_1.1.bb",
            "filepath": "recipes-cgl/vrf",
            "homepage": "",
            "id": 621726,
            "inherits": "autotools siteconfig siteinfo",
            "layerbranch": 166277,
            "license": "GPLv2",
            "pn": "vrf",
            "provides": "vrf ",
            "pv": "1.1",
            "section": "network",
            "summary": "Virtual Route Forwarding foundation package",
            "updated": "2018-04-28T03:04:32+0000"
        },
        {
            "bbclassextend": " ",
            "blacklisted": "",
            "bugtracker": "",
            "description": "The ipsec-test package contains a ipsec-test World program",
            "filename": "ipsec-test_1.0.bb",
            "filepath": "recipes-cut/ipsec-test",
            "homepage": "",
            "id": 621727,
            "inherits": "",
            "layerbranch": 166277,
            "license": "windriver",
            "pn": "ipsec-test",
            "provides": "ipsec-test ",
            "pv": "1.0",
            "section": "apps",
            "summary": "ipsec-test",
            "updated": "2018-04-28T03:04:32+0000"
        },
        {
            "bbclassextend": " ",
            "blacklisted": "",
            "bugtracker": "",
            "description": "The gen-coredump package contains a gen_coredump program",
            "filename": "gen-coredump_1.0.bb",
            "filepath": "recipes-cut/gen-coredump",
            "homepage": "",
            "id": 621728,
            "inherits": "",
            "layerbranch": 166277,
            "license": "windriver",
            "pn": "gen-coredump",
            "provides": "gen-coredump ",
            "pv": "1.0",
            "section": "apps",
            "summary": "gen-coredump",
            "updated": "2018-04-28T03:04:32+0000"
        },
        {
            "bbclassextend": " ",
            "blacklisted": "",
            "bugtracker": "",
            "description": "The cyclictest package contains a Hello World program",
            "filename": "cyclictest_1.0.bb",
            "filepath": "recipes-cut/cyclictest",
            "homepage": "",
            "id": 621729,
            "inherits": "",
            "layerbranch": 166277,
            "license": "windriver",
            "pn": "cyclictest",
            "provides": "cyclictest ",
            "pv": "1.0",
            "section": "apps",
            "summary": "cyclictest",
            "updated": "2018-04-28T03:04:32+0000"
        },
        {
            "bbclassextend": " ",
            "blacklisted": "",
            "bugtracker": "",
            "description": "\tSAF Test is an open-source project serving as the \tcentral location for developing and providing \tconformance test suites for SA Forum published \tspecifications. The test suites cover both the \tA and B version of the HPI and AIS specifications.\tCurrently HPI conformance testsuite has been \tintegrated. \t",
            "filename": "saftest_1.0.8.bb",
            "filepath": "recipes-cut/saftest",
            "homepage": "http://saftest.sourceforge.net/",
            "id": 621730,
            "inherits": "",
            "layerbranch": 166277,
            "license": "GPL-2.0",
            "pn": "saftest",
            "provides": "saftest ",
            "pv": "1.0.8",
            "section": "apps",
            "summary": "HPI Conformance Test Suite",
            "updated": "2018-04-28T03:04:32+0000"
        },
        {
            "bbclassextend": " ",
            "blacklisted": "",
            "bugtracker": "",
            "description": "cgl-unittest",
            "filename": "cgl-unittest_1.0.bb",
            "filepath": "recipes-cut/cgl-unittest",
            "homepage": "",
            "id": 621731,
            "inherits": "",
            "layerbranch": 166277,
            "license": "windriver",
            "pn": "cgl-unittest",
            "provides": "cgl-unittest ",
            "pv": "1.0",
            "section": "apps",
            "summary": "cgl-unittest",
            "updated": "2018-04-28T03:04:32+0000"
        },
        {
            "bbclassextend": " ",
            "blacklisted": "",
            "bugtracker": "",
            "description": "An image which approximates WRLinux glibc-std without graphics.",
            "filename": "wrlinux-image-glibc-cgl.bb",
            "filepath": "recipes-base/images",
            "homepage": "",
            "id": 621732,
            "inherits": "core-image image image-fs_finalize image_types image_types_wic kernel-arch meta populate_sdk_base populate_sdk_ext qemuboot rootfs-postcommands rootfs_ipk siteinfo wrlinux-image wrltemplate_image",
            "layerbranch": 166277,
            "license": "MIT",
            "pn": "wrlinux-image-glibc-cgl",
            "provides": "wrlinux-image-glibc-cgl ",
            "pv": "1.0",
            "section": "base",
            "summary": "",
            "updated": "2018-04-28T03:04:32+0000"
        },
        {
            "bbclassextend": " ",
            "blacklisted": "",
            "bugtracker": "",
            "description": "Wind River Linux core package group: networking",
            "filename": "packagegroup-wr-core-networking.bb",
            "filepath": "recipes-base/packagegroups",
            "homepage": "",
            "id": 621733,
            "inherits": "",
            "layerbranch": 166277,
            "license": "MIT",
            "pn": "packagegroup-wr-core-networking",
            "provides": "packagegroup-wr-core-networking ",
            "pv": "1.0",
            "section": "base",
            "summary": "",
            "updated": "2018-04-28T03:04:33+0000"
        },
        {
            "bbclassextend": " ",
            "blacklisted": "",
            "bugtracker": "",
            "description": "Wind River Linux core package group: cgl testing",
            "filename": "packagegroup-wr-core-cut.bb",
            "filepath": "recipes-base/packagegroups",
            "homepage": "",
            "id": 621734,
            "inherits": "",
            "layerbranch": 166277,
            "license": "MIT",
            "pn": "packagegroup-wr-core-cut",
            "provides": "packagegroup-wr-core-cut ",
            "pv": "1.0",
            "section": "base",
            "summary": "",
            "updated": "2018-04-28T03:04:33+0000"
        },
        {
            "bbclassextend": " ",
            "blacklisted": "",
            "bugtracker": "",
            "description": "Wind River Linux core package group: cgl",
            "filename": "packagegroup-wr-core-cgl.bb",
            "filepath": "recipes-base/packagegroups",
            "homepage": "",
            "id": 621735,
            "inherits": "",
            "layerbranch": 166277,
            "license": "MIT",
            "pn": "packagegroup-wr-core-cgl",
            "provides": "packagegroup-wr-core-cgl ",
            "pv": "1.0",
            "section": "base",
            "summary": "",
            "updated": "2018-04-28T03:04:33+0000"
        }
    ],
    "wrtemplates": [
        {
            "description": "Enable disk quota support",
            "id": 24967,
            "layerbranch": 166277,
            "name": "feature/quota",
            "updated": "2018-04-28T03:04:31+0000"
        },
        {
            "description": "Enable cluster support for lvm2",
            "id": 24968,
            "layerbranch": 166277,
            "name": "feature/clvm",
            "updated": "2018-04-28T03:04:31+0000"
        },
        {
            "description": "Enable 'mip6' support",
            "id": 24969,
            "layerbranch": 166277,
            "name": "feature/mip6",
            "updated": "2018-04-28T03:04:31+0000"
        },
        {
            "description": "Enable libcap-ng",
            "id": 24970,
            "layerbranch": 166277,
            "name": "feature/libcap-ng",
            "updated": "2018-04-28T03:04:31+0000"
        },
        {
            "description": "Enable the various CGL protocol templates",
            "id": 24971,
            "layerbranch": 166277,
            "name": "feature/protocols",
            "updated": "2018-04-28T03:04:31+0000"
        },
        {
            "description": "Enable ipmi",
            "id": 24972,
            "layerbranch": 166277,
            "name": "feature/ipmi",
            "updated": "2018-04-28T03:04:31+0000"
        },
        {
            "description": "Enable all CGL related templates",
            "id": 24973,
            "layerbranch": 166277,
            "name": "feature/cgl-full",
            "updated": "2018-04-28T03:04:31+0000"
        },
        {
            "description": "",
            "id": 24974,
            "layerbranch": 166277,
            "name": "feature/ocfs2",
            "updated": "2018-04-28T03:04:31+0000"
        },
        {
            "description": "Enable the CGL Unit Tests",
            "id": 24975,
            "layerbranch": 166277,
            "name": "feature/cut",
            "updated": "2018-04-28T03:04:31+0000"
        },
        {
            "description": "Enable ATA over Ethernet",
            "id": 24976,
            "layerbranch": 166277,
            "name": "feature/aoe",
            "updated": "2018-04-28T03:04:31+0000"
        },
        {
            "description": "Enable ldap",
            "id": 24977,
            "layerbranch": 166277,
            "name": "feature/ldap",
            "updated": "2018-04-28T03:04:31+0000"
        },
        {
            "description": "Enable VRF (Virtual Routing and Forwarding)",
            "id": 24978,
            "layerbranch": 166277,
            "name": "feature/vrf",
            "updated": "2018-04-28T03:04:31+0000"
        },
        {
            "description": "Enable net-snmp-support",
            "id": 24979,
            "layerbranch": 166277,
            "name": "feature/snmp",
            "updated": "2018-04-28T03:04:31+0000"
        },
        {
            "description": "Enable 'sasl' support",
            "id": 24980,
            "layerbranch": 166277,
            "name": "feature/sasl",
            "updated": "2018-04-28T03:04:31+0000"
        }
    ]
}