{
    "CFG": {
        "BRANCH": "WRLINUX_10_17_BASE_UPDATE0004",
        "CACHE": "config/index-cache/layers_wrs_com",
        "DESCRIPTION": "Wind River Developer Layer Index",
        "TYPE": "restapi-web",
        "URL": "http://layers.wrs.com/layerindex/api/"
    },
    "branches": [
        {
            "bitbake_branch": "WRLINUX_10_17_BASE_UPDATE0004",
            "id": 70,
            "name": "WRLINUX_10_17_BASE_UPDATE0004",
            "short_description": "WRLinux 10_17 Base Update 0004",
            "sort_priority": 9,
            "update_environment": null,
            "updated": "2018-01-17T07:01:53+0000",
            "updates_enabled": true
        }
    ],
    "distros": [],
    "layerBranches": [
        {
            "actual_branch": "",
            "branch": 70,
            "collection": "core",
            "id": 441440,
            "layer": 1,
            "updated": "2018-02-06T13:02:48+0000",
            "vcs_last_commit": "2018-02-02T09:02:56+0000",
            "vcs_last_fetch": "2018-02-06T13:02:48+0000",
            "vcs_last_rev": "11edc004bc66e2f649eed9bfa6769c813c0cb951",
            "vcs_subdir": "meta",
            "version": "11",
            "yp_compatible_version": null
        },
        {
            "actual_branch": "",
            "branch": 70,
            "collection": "signing-key",
            "id": 441592,
            "layer": 129,
            "updated": "2018-02-06T13:02:55+0000",
            "vcs_last_commit": "2017-10-13T07:10:50+0000",
            "vcs_last_fetch": "2018-02-06T13:02:55+0000",
            "vcs_last_rev": "6dd44178fc5cbb6275032d30ccbe348776c89f64",
            "vcs_subdir": "meta-signing-key",
            "version": null,
            "yp_compatible_version": null
        }
    ],
    "layerDependencies": [
        {
            "dependency": 1,
            "id": 32650,
            "layerbranch": 441592,
            "required": true
        }
    ],
    "layerItems": [
        {
            "classic": false,
            "description": "OpenEmbedded-Core is a layer containing the core metadata for current versions\r\nof OpenEmbedded. It is distro-less (can build a functional image with\r\nDISTRO = \"nodistro\") and contains only emulated machine support.",
            "id": 1,
            "index_preference": 1000,
            "layer_type": "A",
            "mailing_list_url": "",
            "name": "openembedded-core",
            "status": "P",
            "summary": "Core Metadata",
            "updated": "2017-08-25T17:08:12+0000",
            "usage_url": "README",
            "vcs_url": "#BASE_URL#/oe-core",
            "vcs_web_file_base_url": "",
            "vcs_web_tree_base_url": "",
            "vcs_web_url": ""
        },
        {
            "classic": false,
            "description": "This layer provides sample keys, by default, are used by build system to sign bootloader,\r\nkernel, IMA signature, RPM and so on. It is used for development and demonstration. The user must know what the risk is to use the sample keys in the product.",
            "id": 129,
            "index_preference": 0,
            "layer_type": "A",
            "mailing_list_url": "",
            "name": "meta-signing-key",
            "status": "P",
            "summary": "User Key Store",
            "updated": "2017-09-01T17:09:28+0000",
            "usage_url": "",
            "vcs_url": "#BASE_URL#/meta-secure-core",
            "vcs_web_file_base_url": "",
            "vcs_web_tree_base_url": "",
            "vcs_web_url": ""
        }
    ],
    "machines": [],
    "recipes": [
        {
            "bbclassextend": "",
            "blacklisted": "",
            "bugtracker": "",
            "description": "Key store for key installation",
            "filename": "key-store_0.1.bb",
            "filepath": "recipes-support/key-store",
            "homepage": "",
            "id": 497686,
            "inherits": "user-key-store",
            "layerbranch": 441592,
            "license": "MIT",
            "pn": "key-store",
            "provides": "key-store ",
            "pv": "0.1",
            "section": "base",
            "summary": "",
            "updated": "2018-01-17T07:01:18+0000"
        }
    ],
    "wrtemplates": []
}