{
    "CFG": {
        "BRANCH": "WRLINUX_9_BASE",
        "CACHE": "config/index-cache/layers_wrs_com",
        "DESCRIPTION": "Wind River Developer Layer Index",
        "TYPE": "restapi-web",
        "URL": "http://layers.wrs.com/layerindex/api/"
    },
    "branches": [
        {
            "bitbake_branch": "wr-9.0-20171109",
            "id": 2,
            "name": "WRLINUX_9_BASE",
            "short_description": "Wind River Linux 9 Baseline",
            "sort_priority": 10,
            "update_environment": null,
            "updated": "2017-11-16T03:11:50+0000",
            "updates_enabled": true
        }
    ],
    "distros": [],
    "layerBranches": [
        {
            "actual_branch": "wr-9.0-20171109",
            "branch": 2,
            "collection": "core",
            "id": 56,
            "layer": 1,
            "updated": "2018-06-26T01:06:13+0000",
            "vcs_last_commit": "2018-06-26T00:06:46+0000",
            "vcs_last_fetch": "2018-06-26T01:06:13+0000",
            "vcs_last_rev": "1011d562a31b1586a5c3036bd53b21d089593187",
            "vcs_subdir": "meta",
            "version": "9",
            "yp_compatible_version": null
        },
        {
            "actual_branch": "wr-9.0-20161130",
            "branch": 2,
            "collection": "filesystems-layer",
            "id": 62,
            "layer": 8,
            "updated": "2018-06-22T14:06:58+0000",
            "vcs_last_commit": "2017-03-15T22:03:48+0000",
            "vcs_last_fetch": "2018-06-22T14:06:58+0000",
            "vcs_last_rev": "bd383c1d7c97f5e6b53262ee2236eedc2baf8900",
            "vcs_subdir": "meta-filesystems",
            "version": "1",
            "yp_compatible_version": null
        },
        {
            "actual_branch": "wr-9.0-20161130",
            "branch": 2,
            "collection": "openembedded-layer",
            "id": 68,
            "layer": 7,
            "updated": "2018-06-22T14:06:57+0000",
            "vcs_last_commit": "2018-01-08T01:01:45+0000",
            "vcs_last_fetch": "2018-06-22T14:06:57+0000",
            "vcs_last_rev": "2a14a0fb044fe493c5a07b75aec3c14def00acaf",
            "vcs_subdir": "meta-oe",
            "version": "1",
            "yp_compatible_version": null
        }
    ],
    "layerDependencies": [
        {
            "dependency": 1,
            "id": 111,
            "layerbranch": 62,
            "required": true
        },
        {
            "dependency": 7,
            "id": 112,
            "layerbranch": 62,
            "required": true
        },
        {
            "dependency": 64,
            "id": 178,
            "layerbranch": 62,
            "required": false
        }
    ],
    "layerItems": [
        {
            "classic": false,
            "description": "OpenEmbedded-Core is a layer containing the core metadata for current versions\r\nof OpenEmbedded. It is distro-less (can build a functional image with\r\nDISTRO = \"nodistro\") and contains only emulated machine support.",
            "id": 1,
            "index_preference": 1000,
            "layer_type": "A",
            "mailing_list_url": "",
            "name": "openembedded-core",
            "status": "P",
            "summary": "Core Metadata",
            "updated": "2018-05-30T18:05:28+0000",
            "usage_url": "README",
            "vcs_url": "#BASE_URL#/oe-core",
            "vcs_web_commit_url": "",
            "vcs_web_file_base_url": "",
            "vcs_web_tree_base_url": "",
            "vcs_web_url": ""
        },
        {
            "classic": false,
            "description": "Additional shared OE metadata",
            "id": 7,
            "index_preference": 0,
            "layer_type": "A",
            "mailing_list_url": "",
            "name": "meta-oe",
            "status": "P",
            "summary": "Additional shared OE metadata",
            "updated": "2018-05-30T17:05:13+0000",
            "usage_url": "README",
            "vcs_url": "#BASE_URL#/meta-openembedded",
            "vcs_web_commit_url": "",
            "vcs_web_file_base_url": "",
            "vcs_web_tree_base_url": "",
            "vcs_web_url": ""
        },
        {
            "classic": false,
            "description": "Filesystem related libraries and programs.  Includes support for FUSE and related components.",
            "id": 8,
            "index_preference": 0,
            "layer_type": "A",
            "mailing_list_url": "",
            "name": "meta-filesystems",
            "status": "P",
            "summary": "Filesystem related libraries and programs",
            "updated": "2018-05-30T17:05:59+0000",
            "usage_url": "README",
            "vcs_url": "#BASE_URL#/meta-openembedded",
            "vcs_web_commit_url": "",
            "vcs_web_file_base_url": "",
            "vcs_web_tree_base_url": "",
            "vcs_web_url": ""
        }
    ],
    "machines": [],
    "recipes": [
        {
            "bbclassextend": "",
            "blacklisted": "",
            "bugtracker": "",
            "description": "",
            "filename": "sshfs-fuse_2.8.bb",
            "filepath": "recipes-filesystems/sshfs-fuse",
            "homepage": "http://fuse.sourceforge.net/sshfs.html",
            "id": 218521,
            "inherits": "autotools pkgconfig siteconfig siteinfo",
            "layerbranch": 62,
            "license": "GPLv2",
            "pn": "sshfs-fuse",
            "provides": "sshfs-fuse ",
            "pv": "2.8",
            "section": "console/network",
            "summary": "This is a filesystem client based on the SSH File Transfer Protocol using FUSE",
            "updated": "2017-06-09T01:06:32+0000"
        },
        {
            "bbclassextend": "",
            "blacklisted": "",
            "bugtracker": "",
            "description": "SMBNetFS is a Linux/FreeBSD filesystem that allow you to use                samba/microsoft network in the same manner as the network                neighborhood in Microsoft Windows. Please donate me to help                in SMBNetFS development.",
            "filename": "smbnetfs_git.bb",
            "filepath": "recipes-filesystems/smbnetfs",
            "homepage": "http://sourceforge.net/projects/smbnetfs",
            "id": 218522,
            "inherits": "autotools gitpkgv pkgconfig siteconfig siteinfo",
            "layerbranch": 62,
            "license": "GPLv2",
            "pn": "smbnetfs",
            "provides": "smbnetfs ",
            "pv": "git",
            "section": "base",
            "summary": "FUSE module for mounting an entire SMB/NMB network in a single directory",
            "updated": "2017-06-09T01:06:32+0000"
        },
        {
            "bbclassextend": "",
            "blacklisted": "",
            "bugtracker": "",
            "description": "",
            "filename": "ifuse_1.1.2.bb",
            "filepath": "recipes-filesystems/ifuse",
            "homepage": "http://www.libimobiledevice.org/",
            "id": 218523,
            "inherits": "autotools pkgconfig siteconfig siteinfo",
            "layerbranch": 62,
            "license": "LGPLv2.1",
            "pn": "ifuse",
            "provides": "ifuse ",
            "pv": "1.1.2",
            "section": "base",
            "summary": "A fuse filesystem to access the contents of an iPhone or iPod Touch",
            "updated": "2017-06-09T01:06:32+0000"
        },
        {
            "bbclassextend": "",
            "blacklisted": "",
            "bugtracker": "",
            "description": "OWFS is an easy way to use the powerful 1-wire system of Dallas/Maxim",
            "filename": "owfs_2.9p1.bb",
            "filepath": "recipes-filesystems/owfs",
            "homepage": "http://www.owfs.org/",
            "id": 218524,
            "inherits": "autotools autotools-brokensep siteconfig siteinfo update-rc.d",
            "layerbranch": 62,
            "license": "GPLv2 & LGPLv2",
            "pn": "owfs",
            "provides": "owfs ",
            "pv": "2.9p1",
            "section": "console/network",
            "summary": "1-Wire file system",
            "updated": "2017-06-09T01:06:32+0000"
        },
        {
            "bbclassextend": "",
            "blacklisted": "",
            "bugtracker": "",
            "description": "",
            "filename": "unionfs-fuse_0.26.bb",
            "filepath": "recipes-filesystems/unionfs-fuse",
            "homepage": "http://podgorny.cz/moin/UnionFsFuse",
            "id": 218525,
            "inherits": "",
            "layerbranch": 62,
            "license": "BSD-3-Clause",
            "pn": "unionfs-fuse",
            "provides": "unionfs-fuse ",
            "pv": "0.26",
            "section": "console/network",
            "summary": "A FUSE based implemention of unionfs",
            "updated": "2017-06-09T01:06:32+0000"
        },
        {
            "bbclassextend": "native",
            "blacklisted": "",
            "bugtracker": "",
            "description": "Tools for managing 'yaffs2' file systems.",
            "filename": "yaffs2-utils_git.bb",
            "filepath": "recipes-filesystems/yaffs2",
            "homepage": "http://www.yaffs.net",
            "id": 218526,
            "inherits": "",
            "layerbranch": 62,
            "license": "GPLv2",
            "pn": "yaffs2-utils",
            "provides": "yaffs2-utils ",
            "pv": "0.0+gitX",
            "section": "base",
            "summary": "Yet Another Flash File System",
            "updated": "2017-06-09T01:06:32+0000"
        },
        {
            "bbclassextend": "",
            "blacklisted": "",
            "bugtracker": "",
            "description": "SIMPLE-MTPFS is a FUSE based filsystem for MTP devices connected via USB",
            "filename": "simple-mtpfs_git.bb",
            "filepath": "recipes-filesystems/simple-mtpfs",
            "homepage": "https://github.com/phatina/simple-mtpfs",
            "id": 218527,
            "inherits": "autotools pkgconfig siteconfig siteinfo",
            "layerbranch": 62,
            "license": "GPLv2",
            "pn": "simple-mtpfs",
            "provides": "simple-mtpfs ",
            "pv": "git",
            "section": "base",
            "summary": "",
            "updated": "2017-06-09T01:06:32+0000"
        },
        {
            "bbclassextend": "",
            "blacklisted": "",
            "bugtracker": "",
            "description": "The NTFS-3G driver is an open source, freely available NTFS driver for Linux with read and write support.",
            "filename": "ntfs-3g-ntfsprogs_2013.1.13.bb",
            "filepath": "recipes-filesystems/ntfs-3g-ntfsprogs",
            "homepage": "http://www.ntfs-3g.org/",
            "id": 218528,
            "inherits": "autotools pkgconfig siteconfig siteinfo",
            "layerbranch": 62,
            "license": "GPLv2 & LGPLv2",
            "pn": "ntfs-3g-ntfsprogs",
            "provides": "ntfs-3g-ntfsprogs ntfsprogs ntfs-3g",
            "pv": "2013.1.13",
            "section": "base",
            "summary": "",
            "updated": "2017-06-09T01:06:32+0000"
        },
        {
            "bbclassextend": "native nativesdk",
            "blacklisted": "",
            "bugtracker": "",
            "description": "LogFS is a Linux log-structured and scalable flash file system, intended for use on large devices of flash memory. It is written by J\u00f6rn Engel and in part sponsored by the CE Linux Forum. LogFS is included in the mainline Linux kernel and was introduced in version 2.6.34, released on May 16, 2010.",
            "filename": "logfsprogs_git.bb",
            "filepath": "recipes-filesystems/logfsprogs",
            "homepage": "https://github.com/prasad-joshi/logfsprogs",
            "id": 218529,
            "inherits": "",
            "layerbranch": 62,
            "license": "GPLv2",
            "pn": "logfsprogs",
            "provides": "logfsprogs ",
            "pv": "git",
            "section": "base",
            "summary": "LogFS Programs: used to create LogFS file system",
            "updated": "2017-06-09T01:06:32+0000"
        },
        {
            "bbclassextend": "",
            "blacklisted": "",
            "bugtracker": "",
            "description": "fuse-exfat is a read and write driver implementing the extended file allocation table as a filesystem in userspace. A mounthelper is provided under the name mount.exfat-fuse. ",
            "filename": "fuse-exfat_1.2.3.bb",
            "filepath": "recipes-filesystems/fuse-exfat",
            "homepage": "http://code.google.com/p/exfat/",
            "id": 218530,
            "inherits": "autotools pkgconfig siteconfig siteinfo",
            "layerbranch": 62,
            "license": "GPLv2+",
            "pn": "fuse-exfat",
            "provides": "fuse-exfat ",
            "pv": "1.2.3",
            "section": "universe/otherosfs",
            "summary": "read and write exFAT driver for FUSE",
            "updated": "2017-06-09T01:06:33+0000"
        },
        {
            "bbclassextend": "",
            "blacklisted": "",
            "bugtracker": "",
            "description": "FUSE (Filesystem in Userspace) is a simple interface for userspace                programs to export a virtual filesystem to the Linux kernel. FUSE                also aims to provide a secure method for non privileged users to                create and mount their own filesystem implementations.               ",
            "filename": "fuse_2.9.4.bb",
            "filepath": "recipes-support/fuse",
            "homepage": "https://github.com/libfuse/libfuse",
            "id": 218531,
            "inherits": "autotools pkgconfig siteconfig siteinfo systemd update-rc.d",
            "layerbranch": 62,
            "license": "GPLv2 & LGPLv2.1",
            "pn": "fuse",
            "provides": "fuse ",
            "pv": "2.9.4",
            "section": "libs",
            "summary": "Implementation of a fully functional filesystem in a userspace program",
            "updated": "2017-06-09T01:06:33+0000"
        },
        {
            "bbclassextend": "",
            "blacklisted": "",
            "bugtracker": "",
            "description": "",
            "filename": "physfs_git.bb",
            "filepath": "recipes-support/physfs",
            "homepage": "",
            "id": 218532,
            "inherits": "cmake",
            "layerbranch": 62,
            "license": "Zlib",
            "pn": "physfs",
            "provides": "physfs ",
            "pv": "2.0.3+gitX",
            "section": "base",
            "summary": "PhysicsFS is a library to provide abstract access to various archives",
            "updated": "2017-06-09T01:06:33+0000"
        },
        {
            "bbclassextend": "",
            "blacklisted": "",
            "bugtracker": "",
            "description": "",
            "filename": "xfsprogs_4.7.0.bb",
            "filepath": "recipes-utils/xfsprogs",
            "homepage": "http://oss.sgi.com/projects/xfs",
            "id": 218533,
            "inherits": "autotools autotools-brokensep siteconfig siteinfo",
            "layerbranch": 62,
            "license": "GPLv2 & LGPLv2.1",
            "pn": "xfsprogs",
            "provides": "xfsprogs ",
            "pv": "4.7.0",
            "section": "base",
            "summary": "XFS Filesystem Utilities",
            "updated": "2017-06-09T01:06:33+0000"
        },
        {
            "bbclassextend": "native",
            "blacklisted": "",
            "bugtracker": "",
            "description": "xorriso copies file objects from POSIX compliant filesystems into Rock Ridge enhanced ISO 9660 filesystems and allows session-wise manipulation of such filesystems",
            "filename": "xorriso_1.4.0.bb",
            "filepath": "recipes-utils/xorriso",
            "homepage": "",
            "id": 218534,
            "inherits": "autotools autotools-brokensep distro_features_check pkgconfig siteconfig siteinfo",
            "layerbranch": 62,
            "license": "GPLv3",
            "pn": "xorriso",
            "provides": "xorriso ",
            "pv": "1.4.0",
            "section": "base",
            "summary": "",
            "updated": "2017-06-09T01:06:33+0000"
        },
        {
            "bbclassextend": "native",
            "blacklisted": "",
            "bugtracker": "",
            "description": "",
            "filename": "f2fs-tools_1.4.0.bb",
            "filepath": "recipes-utils/f2fs-tools",
            "homepage": "http://sourceforge.net/projects/f2fs-tools/",
            "id": 218535,
            "inherits": "autotools pkgconfig siteconfig siteinfo",
            "layerbranch": 62,
            "license": "GPLv2",
            "pn": "f2fs-tools",
            "provides": "f2fs-tools ",
            "pv": "1.4.0",
            "section": "base",
            "summary": "Tools for Flash-Friendly File System (F2FS)",
            "updated": "2017-06-09T01:06:33+0000"
        },
        {
            "bbclassextend": "",
            "blacklisted": "",
            "bugtracker": "",
            "description": "Utilities to manage extended file allocation table filesystem. This package provides tools to create, check and label the filesystem. It contains  - dumpexfat to dump properties of the filesystem  - exfatfsck / fsck.exfat to report errors found on a exFAT filesystem  - exfatlabel to label a exFAT filesystem  - mkexfatfs / mkfs.exfat to create a exFAT filesystem. ",
            "filename": "exfat-utils_1.2.3.bb",
            "filepath": "recipes-utils/exfat-utils",
            "homepage": "http://code.google.com/p/exfat/",
            "id": 218536,
            "inherits": "autotools pkgconfig siteconfig siteinfo",
            "layerbranch": 62,
            "license": "GPLv2",
            "pn": "exfat-utils",
            "provides": "exfat-utils ",
            "pv": "1.2.3",
            "section": "universe/otherosfs",
            "summary": "utilities to create, check, label and dump exFAT filesystem",
            "updated": "2017-06-09T01:06:33+0000"
        },
        {
            "bbclassextend": "native",
            "blacklisted": "",
            "bugtracker": "",
            "description": "",
            "filename": "aufs-util_git.bb",
            "filepath": "recipes-utils/aufs-util",
            "homepage": "http://aufs.sourceforge.net/",
            "id": 218537,
            "inherits": "",
            "layerbranch": 62,
            "license": "GPLv2",
            "pn": "aufs-util",
            "provides": "aufs-util ",
            "pv": "3.14+gitX",
            "section": "base",
            "summary": "Tools for managing AUFS mounts",
            "updated": "2017-06-09T01:06:33+0000"
        },
        {
            "bbclassextend": "",
            "blacklisted": "",
            "bugtracker": "",
            "description": "The xfsdump package contains xfsdump, xfsrestore and a                number of other utilities for administering XFS filesystems.               xfsdump examines files in a filesystem, determines which                need to be backed up, and copies those files to a                specified disk, tape or other storage medium.",
            "filename": "xfsdump_3.1.6.bb",
            "filepath": "recipes-utils/xfsdump",
            "homepage": "http://oss.sgi.com/projects/xfs",
            "id": 218538,
            "inherits": "autotools autotools-brokensep siteconfig siteinfo",
            "layerbranch": 62,
            "license": "GPLv2",
            "pn": "xfsdump",
            "provides": "xfsdump ",
            "pv": "3.1.6",
            "section": "base",
            "summary": "XFS Filesystem Dump Utility",
            "updated": "2017-06-09T01:06:33+0000"
        },
        {
            "bbclassextend": "",
            "blacklisted": "",
            "bugtracker": "",
            "description": "The Data Management API (DMAPI/XDSM) allows implementation                of hierarchical storage management software with no kernel                modifications as well as high-performance dump programs                without requiring \"raw\" access to the disk and knowledge                of filesystem structures.This interface is implemented by                the libdm library.",
            "filename": "dmapi_2.2.12.bb",
            "filepath": "recipes-utils/dmapi",
            "homepage": "http://oss.sgi.com/projects/xfs",
            "id": 218539,
            "inherits": "autotools autotools-brokensep siteconfig siteinfo",
            "layerbranch": 62,
            "license": "LGPLv2.1",
            "pn": "dmapi",
            "provides": "dmapi ",
            "pv": "2.2.12",
            "section": "base",
            "summary": "Library functions to get attribute bits",
            "updated": "2017-06-09T01:06:33+0000"
        }
    ],
    "wrtemplates": []
}